{
  "version": "1.0",
  "defaultProvider": "cdnjs",
  "libraries": [
    {
      "library": "twitter-bootstrap@3.3.7",
      "destination": "wwwroot/lib/twitter-bootstrap/"
    },
    {
      "library": "jquery@2.2.0",
      "destination": "wwwroot/lib/jquery/"
    },
    {
      "library": "fontawesome-iconpicker@3.2.0",
      "destination": "wwwroot/lib/fontawesome-iconpicker/"
    },
    {
      "library": "font-awesome@5.10.2",
      "destination": "wwwroot/lib/font-awesome/"
    },
    {
      "library": "jquery-loading-overlay@2.1.6",
      "destination": "wwwroot/lib/jquery-loading-overlay/"
    }
  ]
}